tryton_analyzer/__init__.py
tryton_analyzer/analyzer.py
tryton_analyzer/parsing.py
tryton_analyzer/pool.py
tryton_analyzer/pool_companion.py
tryton_analyzer/tools.py
tryton_analyzer/tryton_lint.py
tryton_analyzer/tryton_ls.py
tryton_analyzer-0.1.0.dist-info/LICENSE
tryton_analyzer-0.1.0.dist-info/METADATA
tryton_analyzer-0.1.0.dist-info/WHEEL
tryton_analyzer-0.1.0.dist-info/entry_points.txt
tryton_analyzer-0.1.0.dist-info/RECORD
